eplus_rmd/ASHRAE229.schema.json
eplus_rmd/ASHRAE229_extra.schema.json
eplus_rmd/ASHRAE229_extra.schema.yaml
eplus_rmd/Enumerations2019ASHRAE901.schema.json
eplus_rmd/Enumerations2019T24.schema.json
eplus_rmd/EnumerationsRESNET.schema.json
eplus_rmd/Output2019ASHRAE901.schema.json
eplus_rmd/__init__.py
eplus_rmd/energyplus_implementation_report.txt
eplus_rmd/input_file.py
eplus_rmd/output_file.py
eplus_rmd/runner.py
eplus_rmd/status_reporter.py
eplus_rmd/translator.py
eplus_rmd/validator.py
eplus_rmd/example/ASHRAE901_OfficeSmall_STD2019_Denver.epJSON
eplus_rmd/example/ASHRAE901_OfficeSmall_STD2019_Denver.idf
eplus_rmd/example/ASHRAE901_OfficeSmall_STD2019_Denver.rmd
eplus_rmd/example/ASHRAE901_OfficeSmall_STD2019_Denvermtr.csv
eplus_rmd/example/ASHRAE901_OfficeSmall_STD2019_Denverout.audit
eplus_rmd/example/ASHRAE901_OfficeSmall_STD2019_Denverout.bnd
eplus_rmd/example/ASHRAE901_OfficeSmall_STD2019_Denverout.csv
eplus_rmd/example/ASHRAE901_OfficeSmall_STD2019_Denverout.eio
eplus_rmd/example/ASHRAE901_OfficeSmall_STD2019_Denverout.end
eplus_rmd/example/ASHRAE901_OfficeSmall_STD2019_Denverout.err
eplus_rmd/example/ASHRAE901_OfficeSmall_STD2019_Denverout.eso
eplus_rmd/example/ASHRAE901_OfficeSmall_STD2019_Denverout.json
eplus_rmd/example/ASHRAE901_OfficeSmall_STD2019_Denverout.mdd
eplus_rmd/example/ASHRAE901_OfficeSmall_STD2019_Denverout.mtd
eplus_rmd/example/ASHRAE901_OfficeSmall_STD2019_Denverout.mtr
eplus_rmd/example/ASHRAE901_OfficeSmall_STD2019_Denverout.rdd
eplus_rmd/example/ASHRAE901_OfficeSmall_STD2019_Denverout.rvaudit
eplus_rmd/example/ASHRAE901_OfficeSmall_STD2019_Denverout.shd
eplus_rmd/example/ASHRAE901_OfficeSmall_STD2019_Denverout_hourly.json
eplus_rmd/example/ASHRAE901_OfficeSmall_STD2019_Denverssz.csv
eplus_rmd/example/ASHRAE901_OfficeSmall_STD2019_Denvertbl.htm
eplus_rmd/example/ASHRAE901_OfficeSmall_STD2019_Denverzsz.csv
eplus_rmd-0.2.dist-info/LICENSE
eplus_rmd-0.2.dist-info/METADATA
eplus_rmd-0.2.dist-info/WHEEL
eplus_rmd-0.2.dist-info/entry_points.txt
eplus_rmd-0.2.dist-info/top_level.txt
eplus_rmd-0.2.dist-info/RECORD
