Metadata-Version: 2.1
Name: eplus-rmd
Version: 0.2
Summary: A Python tool for generating RMDs.
Home-page: https://github.com/JasonGlazer/createRulesetModelDescription
Author: Jason Glazer
Author-email: 
License: UNKNOWN
Keywords: energyplus
Platform: UNKNOWN
Requires-Python: >=3.7
License-File: LICENSE
Requires-Dist: jsonschema
Requires-Dist: pyyaml
